messaging/__init__.py
messaging/influx_client.py
messaging/message.py
messaging/pull.py
messaging/setup.py
zmq-lightweight-messaging/__init__.py
zmq-lightweight-messaging/influx_client.py
zmq-lightweight-messaging/message.py
zmq-lightweight-messaging/pull.py
zmq-lightweight-messaging/setup.py
zmq_lightweight_messaging/__init__.py
zmq_lightweight_messaging/influx_client.py
zmq_lightweight_messaging/message.py
zmq_lightweight_messaging/pull.py
zmq_lightweight_messaging/setup.py
zmq_lightweight_messaging-0.4.dist-info/METADATA
zmq_lightweight_messaging-0.4.dist-info/WHEEL
zmq_lightweight_messaging-0.4.dist-info/top_level.txt
zmq_lightweight_messaging-0.4.dist-info/RECORD
