Metadata-Version: 2.1
Name: zmq-lightweight-messaging
Version: 0.4
Summary: Lightweight messaging framework based on ZMQ
Home-page: UNKNOWN
Author: siddharthsurelia13
Author-email: siddharthsurelia13@gmail.com
License: MIT
Platform: UNKNOWN
Requires-Dist: zmq
